Workbook

Sheet Overview
A1: Task 1 - Test Design & Risk Coverage: Local Fund Transfer
A3: Author | B3: Saleh Desouky
A4: Version | B4: 1.0
A5: Input | B5: User story and acceptance criteria AC1-AC6 as received from the BA. No other documentation was available.
A6: How to read this workbook | B6: 1.1 Questions -> Requirements -> 1.2 Risk Register -> 1.3 Test Cases -> Traceability -> 1.4 Coverage. Each test case is linked to the acceptance criteria / implicit requirements it verifies (AC1-AC6, IR1-IR6) and to the risks it reduces (R1-R6).
A8: Risk scoring model
A9: Likelihood (1-3) | B9: 1 = unlikely given normal controls; 2 = plausible; 3 = likely, because the requirement leaves the behaviour undefined.
A10: Impact (1-3) | B10: 1 = inconvenience; 2 = customer blocked or confused, no money lost; 3 = funds lost or wrongly moved, or a fraud / regulatory control weakened.
A11: Score and rating | B11: Score = Likelihood x Impact. High = 6-9, Medium = 3-5, Low = 1-2.
A12: Tie-break (test order) | B12: Equal scores are ordered by impact first (Impact 3 before Impact 2), then by how far the damage spreads: controls protecting other customers' money (R4) before authorisation (R3) before limits (R2). The resulting order is in the Test order column of the risk register.
A13: Note | B13: Scores are my judgement from the requirement alone. I would recalibrate them with the team once architecture and defect history are known.
A14: Common preconditions (CP) | B14: Customer logged in; active local-currency account with a known balance; at least one registered, active beneficiary; no transfers yet today unless the case says otherwise. Balances are verified in the ledger / statement, not only on screen.
A16: Assumptions | B16: Test amounts and boundaries in 1.3 rely on the fallback assumptions in 1.1 (inclusive limits, calendar-day window, fee in the balance check). They must be re-checked when the BA answers.

Sheet 1.1 Questions
A1: # | B1: Question for BA / PO | C1: Why it matters | D1: Assumption if unanswered | E1: Status
A2: Q1 | B2: Are the limits inclusive (is exactly 10,000 allowed)? Which currency are they in? | C2: Defines the boundary values. | D2: Inclusive, in local currency. | E2: Open
A3: Q2 | B3: Is the daily limit a calendar day (which time zone) or a rolling 24 hours? Do pending or failed transfers count? | C3: The same history gives different results under each rule. | D3: Calendar day in the bank's local time. Pending counts; failed does not. | E3: Open
A4: Q3 | B4: Is the fee part of the limit and of the balance check? Is it shown before OTP? | C4: Otherwise the account can go negative, or the customer pays an amount they never saw. | D4: Not part of the limit; included in the balance check; shown before OTP. | E4: Open
A5: Q4 | B5: What happens when funds are insufficient? No AC covers it. | C5: The most common failure is unspecified. | D5: Rejected before OTP with a specific message. | E5: Open
A6: Q5 | B6: Same-bank only, or other local banks too? Does success mean debited, or credited to the beneficiary? | C6: Interbank transfers settle asynchronously and can fail after the debit. | D6: Both. Success = debited and accepted; status may be pending. | E6: Open
A7: Q6 | B7: If a transfer fails after the debit, is it reversed automatically? What does the customer see? | C7: AC6 ('an error message') is the biggest gap. A vague error after a debit leads to retries and double payments. | D7: No money is lost; the customer sees a clear status, not a generic error. | E7: Open
A8: Q7 | B8: OTP rules: validity, attempts, resend limit. Is the OTP tied to this specific transfer? | C8: It is the only authorisation step. | D8: A few minutes, 3 attempts, single use, tied to the transfer details. | E8: Open
A9: Q8 | B9: What happens on a double tap or a network retry? | C9: Without duplicate protection a retry becomes a second debit. | D9: Backend deduplicates: one action = at most one debit. | E9: Open
A10: Q9 | B10: Which source accounts are eligible (types, currencies, frozen or dormant)? | C10: A foreign-currency source makes this an FX transfer, a different feature. | D10: Active local-currency current and savings accounts only. | E10: Open
A11: Q10 | B11: Is there a cooling-off period or lower limit for newly added beneficiaries? | C11: A common control; if it exists it is a limit rule to test. | D11: None assumed; logged as an open risk. | E11: Open
A12: Q11 | B12: Amount format: minimum, decimals, Arabic-Indic digits, separators? | C12: Defines the input partitions; rounding is a money error. | D12: Minimum 0.01, max 2 decimals, otherwise rejected (not rounded). | E12: Open
A13: Q12 | B13: AC1 makes the purpose an optional note, but the payments API (Task 3) requires a purposeCode. Which is right? | C13: Purpose codes are often needed for reporting; a mismatch breaks transfers or reporting. | D13: Raised as a contradiction, not assumed away. | E13: Open
B15: Lower priority: does an SMS failure affect the transfer (it must not)? What must the SMS contain? Cut-off times and holidays for interbank? Is there an OTP test hook in non-production environments for automation?

Sheet Requirements
A1: ID | B1: Type | C1: Requirement | D1: Source
A2: AC1 | B2: Acceptance criterion | C2: Transfer initiation: customer selects a source account, a registered beneficiary, enters an amount and an optional purpose note. | D2: BA requirement
A3: AC2 | B3: Acceptance criterion | C3: Transfer is confirmed with a One-Time Password before execution. | D3: BA requirement
A4: AC3 | B4: Acceptance criterion | C4: A transfer fee is applied according to the bank's fee configuration. | D4: BA requirement
A5: AC4 | B5: Acceptance criterion | C5: Daily transfer limit 20,000; per-transaction limit 10,000. | D5: BA requirement
A6: AC5 | B6: Acceptance criterion | C6: On success: source debited, reference generated, confirmation screen shown, confirmation SMS sent. | D6: BA requirement
A7: AC6 | B7: Acceptance criterion | C7: If the transfer cannot be completed, the customer is shown an error message. | D7: BA requirement
A8: IR1 | B8: Implicit requirement | C8: Insufficient funds are rejected before OTP, with the fee included in the balance check. | D8: Q3, Q4
A9: IR2 | B9: Implicit requirement | C9: A failure after the debit loses no money: either nothing is debited or the debit is reversed automatically. | D9: Q5, Q6
A10: IR3 | B10: Implicit requirement | C10: An OTP is valid only for the transfer details it was issued for. | D10: Q7
A11: IR4 | B11: Implicit requirement | C11: A duplicate submission or retry results in at most one debit. | D11: Q8
A12: IR5 | B12: Implicit requirement | C12: Limits hold when transfers are submitted at the same time. | D12: Q2
A13: IR6 | B13: Implicit requirement | C13: A customer can transfer only from their own accounts to their own registered beneficiaries (enforced by the service, not just the UI). | D13: Implied by AC1
C15: Implicit requirements are behaviours the acceptance criteria do not state but a money-transfer feature must have. Each one came out of a question in 1.1 and stays an assumption until the BA / PO confirms it.

Sheet 1.2 Risk Register
A1: Risk ID | B1: Risk | C1: Cause | D1: Likelihood (1-3) | E1: Impact (1-3) | F1: Score | G1: Rating | H1: Impact on customer | I1: Impact on bank | J1: Impact on us (delivery partner) | K1: Covered by | L1: Owner | M1: Test order
A2: R1 | B2: Partial failure: account debited but transfer fails, no reversal, customer retries | C2: AC5/AC6 describe only the happy path and a generic error | D2: 3 | E2: 3 | F2: =D2*E2 -> 9 | G2: =IF(F2>=6,"High",IF(F2>=3,"Medium","Low")) -> High | H2: Loses money or pays twice | I2: Reconciliation breaks, complaints, regulator attention | J2: Severity-1 incident from our release | K2: TC01, TC07, TC08 | L2: QA Lead | M2: 1
A3: R2 | B3: Limits not enforced correctly (boundary, daily window, pending transfers, simultaneous requests) | C3: Limit rules only partly specified (Q1, Q2) | D3: 2 | E3: 3 | F3: =D3*E3 -> 6 | G3: =IF(F3>=6,"High",IF(F3>=3,"Medium","Low")) -> High | H3: Can move more than policy allows | I3: Policy breach, larger fraud losses | J3: Boundary defects are what testing should catch | K3: TC02, TC03, TC09, TC11 | L3: QA Lead | M3: 4
A4: R3 | B4: OTP does not protect the transfer the customer actually approved | C4: OTP rules unspecified (Q7) | D4: 2 | E4: 3 | F4: =D4*E4 -> 6 | G4: =IF(F4>=6,"High",IF(F4>=3,"Medium","Low")) -> High | H4: Unauthorised transfers | I4: Fraud liability | J4: Reputation | K4: TC05, TC06 | L4: QA Lead | M4: 3
A5: R4 | B5: Account-ownership checks: customer can only use their own accounts and beneficiaries | C5: Server-side checks not mentioned in the AC | D5: 2 | E5: 3 | F5: =D5*E5 -> 6 | G5: =IF(F5>=6,"High",IF(F5>=3,"Medium","Low")) -> High | H5: Another customer's money moved | I5: Security incident | J5: Critical finding | K5: TC11, TC12 | L5: QA Lead | M5: 2
A6: R5 | B6: Misleading result: generic error when money moved, or success SMS for a failed transfer | C6: AC6 too vague | D6: 3 | E6: 2 | F6: =D6*E6 -> 6 | G6: =IF(F6>=6,"High",IF(F6>=3,"Medium","Low")) -> High | H6: Panic, duplicate retries (feeds R1) | I6: Call-centre load | J6: Perceived low quality | K6: TC01, TC08 | L6: QA Lead | M6: 5
A7: R6 | B7: Fee or amount mismatch, or rounding | C7: Fee rules referenced but not defined (AC3, Q3, Q11) | D7: 2 | E7: 2 | F7: =D7*E7 -> 4 | G7: =IF(F7>=6,"High",IF(F7>=3,"Medium","Low")) -> Medium | H7: Overcharged | I7: Refunds, conduct risk | J7: Rework | K7: TC01, TC04, TC10 | L7: QA Lead | M7: 6
B9: Why R1 ranks first: the requirement describes only the happy path and a vague failure. Partial failure is where real money incidents happen, and it is exactly what is undefined. R2-R4 are controls: when they fail the bank loses a safeguard, not just a feature. Equal scores are ordered by the tie-break rule on the Overview sheet (see Test order).
B10: Likelihood and Impact (blue) are inputs; Score and Rating are formulas. Scale definitions are on the Overview sheet.

Sheet 1.3 Test Cases
A1: Test ID | B1: Title | C1: Requirement | D1: Risk | E1: Priority | F1: Preconditions | G1: Test data | H1: Steps | I1: Expected result | J1: Level | K1: Execution | L1: Status
A2: TC01 | B2: Successful transfer: money moves once and every record agrees | C2: AC1, AC2, AC3, AC5 | D2: R1, R5, R6 | E2: P1 | F2: Common preconditions (CP). Balance 5,000.00; fee F known from configuration. | G2: Amount 1,500.75; purpose note 'Rent' | H2: 1. Select source account and beneficiary 2. Enter amount and note 3. Review the summary 4. Enter valid OTP | I2: Fee F shown before OTP. Balance reduced by 1,500.75 + F (amount and fee as separate entries). One unique reference. Confirmation screen, history and SMS show the same amount, fee and reference. Beneficiary credited (same bank) or status pending (other bank). | J2: UI + ledger | K2: Automated (UI smoke); SMS content manual | L2: Not run
A3: TC02 | B3: Per-transaction limit boundary | C3: AC4, AC6 | D3: R2 | E3: P1 | F3: Common preconditions (CP). Balance >= 10,100. | G3: 9,999.99 / 10,000.00 / 10,000.01 | H3: 1. Submit a transfer for each amount in turn | I3: First two succeed. 10,000.01 rejected before an OTP is sent, with a limit-specific message. No debit; daily usage unchanged. | J3: API | K3: Automated | L3: Not run
A4: TC03 | B4: Daily limit: totals, exclusions and reset | C4: AC4, AC6 | D4: R2 | E4: P1 | F4: Common preconditions (CP). Today: successful transfers totalling 15,000 plus one failed transfer of 3,000. | G4: 5,000.00, then 0.01; next day 0.01 | H4: 1. Transfer 5,000.00 2. Transfer 0.01 3. Next calendar day (bank time zone): transfer 0.01 | I4: 5,000 succeeds (exactly 20,000; failed transfer not counted). 0.01 rejected with a daily-limit message. Next day 0.01 succeeds. | J4: API (date control) | K4: Automated | L4: Not run
A5: TC04 | B5: Fee included in the balance check | C5: AC3, AC6, IR1 | D5: R6 | E5: P1 | F5: Common preconditions (CP). Account A balance = amount + fee; account B balance = amount + fee - 0.01. | G5: Amount 1,000.00; fee F | H5: 1. Transfer from account A 2. Transfer from account B | I5: A succeeds, leaving 0.00. B rejected for insufficient funds before OTP; no debit and no hold remains. | J5: API | K5: Automated | L5: Not run
A6: TC05 | B6: OTP: wrong, expired, attempts exhausted, replaced by a resend | C6: AC2, AC6 | D6: R3 | E6: P1 | F6: Common preconditions (CP). Transfer at the OTP step. | G6: Wrong OTP; expired OTP; old OTP after resend | H6: 1. Enter a wrong OTP 2. Enter an expired OTP 3. Repeat wrong OTP to the attempt limit 4. Request resend, then enter the old OTP | I6: Each attempt rejected with the correct message; after the limit the transfer is cancelled. No debit and no reference in any case. | J6: UI + API | K6: Automated (needs OTP test hook) | L6: Not run
A7: TC06 | B7: OTP covers only the details the customer approved | C7: AC2, IR3 | D7: R3 | E7: P1 | F7: Common preconditions (CP). OTP issued for amount X to beneficiary B1. | G7: Change to amount Y or beneficiary B2 | H7: 1. Reach the OTP step 2. Go back and change amount or beneficiary 3. Enter the original OTP | I7: Original OTP no longer valid; a new confirmation is required for the new details. Nothing executed with the original OTP. | J7: UI + API | K7: Automated (needs OTP test hook) | L7: Not run
A8: TC07 | B8: Duplicate submission | C8: AC5, IR4 | D8: R1 | E8: P1 | F8: Common preconditions (CP). | G8: Amount 500.00 | H8: 1. Tap Confirm twice quickly 2. Repeat with the connection dropped and restored during submit | I8: Exactly one debit and one reference in each case; the repeat shows the existing result. | J8: UI + API | K8: Automated | L8: Not run
A9: TC08 | B9: Failure after OTP is handled safely | C9: AC6, IR2 | D9: R1, R5 | E9: P1 | F9: Common preconditions (CP). Test environment able to simulate core-banking or beneficiary-bank failure. | G9: Amount 750.00 | H9: 1. Configure the downstream failure / timeout 2. Complete a transfer with valid OTP 3. Check ledger, customer status and SMS | I9: Either nothing debited, or debit reversed within the agreed time. Customer sees a clear status (failed / processing); no success SMS. | J9: Integration | K9: Manual with dev support; automate once a stub exists | L9: Not run
A10: TC09 | B10: Simultaneous transfers near the daily limit | C10: AC4, IR5 | D10: R2 | E10: P1 | F10: Common preconditions (CP). 10,000 of the daily limit remaining. | G10: Two transfers of 6,000 at the same time | H10: 1. Submit both transfers simultaneously from two sessions | I10: Exactly one succeeds; daily total never exceeds 20,000. | J10: API | K10: Automated | L10: Not run
A11: TC10 | B11: Amount input partitions | C11: AC1, AC6 | D11: R6 | E11: P2 | F11: Common preconditions (CP). | G11: 0; -50; 100.005; 'abc'; 00100; 1,000.50; Arabic-Indic digits | H11: 1. Enter each value in the amount field and continue | I11: Each value is either rejected with a clear message or interpreted correctly and consistently. Amount debited always equals the amount confirmed. | J11: API + UI | K11: Automated (data-driven) | L11: Not run
A12: TC11 | B12: State changes during the flow | C12: AC1, AC6 | D12: R2, R4 | E12: P2 | F12: Common preconditions (CP). | G12: Beneficiary removed; account frozen | H12: 1. Start a transfer and reach the OTP step 2. In another channel remove the beneficiary / freeze the account 3. Enter the OTP | I12: Transfer rejected at execution with a specific message; no debit. | J12: API | K12: Automated | L12: Not run
A13: TC12 | B13: Only the customer's own accounts and beneficiaries can be used | C13: AC1, IR6 | D13: R4 | E13: P1 | F13: Common preconditions (CP). A second test customer with their own account and beneficiary. | G13: Customer A and customer B identifiers | H13: 1. As customer A, review the account and beneficiary lists 2. Attempt a transfer referencing an account or beneficiary that belongs to customer B | I13: Lists show only customer A's own items. The service rejects the transfer; nothing is debited from either customer. | J13: API | K13: Automated | L13: Not run

Sheet Traceability
A1: Requirements traceability: acceptance criteria and implicit requirements -> test cases
A2: ID | B2: Description | C2: TC01 | D2: TC02 | E2: TC03 | F2: TC04 | G2: TC05 | H2: TC06 | I2: TC07 | J2: TC08 | K2: TC09 | L2: TC10 | M2: TC11 | N2: TC12 | O2: Tests | P2: Coverage
A3: =Requirements!A2 -> AC1 | B3: =Requirements!C2 -> Transfer initiation: customer selects a source account, a registered beneficiary, enters an amount and an optional purpose note. | C3: =IF(ISNUMBER(SEARCH($A3,'1.3 Test Cases'!$C$2)),"X","") -> X | D3: =IF(ISNUMBER(SEARCH($A3,'1.3 Test Cases'!$C$3)),"X","") | E3: =IF(ISNUMBER(SEARCH($A3,'1.3 Test Cases'!$C$4)),"X","") | F3: =IF(ISNUMBER(SEARCH($A3,'1.3 Test Cases'!$C$5)),"X","") | G3: =IF(ISNUMBER(SEARCH($A3,'1.3 Test Cases'!$C$6)),"X","") | H3: =IF(ISNUMBER(SEARCH($A3,'1.3 Test Cases'!$C$7)),"X","") | I3: =IF(ISNUMBER(SEARCH($A3,'1.3 Test Cases'!$C$8)),"X","") | J3: =IF(ISNUMBER(SEARCH($A3,'1.3 Test Cases'!$C$9)),"X","") | K3: =IF(ISNUMBER(SEARCH($A3,'1.3 Test Cases'!$C$10)),"X","") | L3: =IF(ISNUMBER(SEARCH($A3,'1.3 Test Cases'!$C$11)),"X","") -> X | M3: =IF(ISNUMBER(SEARCH($A3,'1.3 Test Cases'!$C$12)),"X","") -> X | N3: =IF(ISNUMBER(SEARCH($A3,'1.3 Test Cases'!$C$13)),"X","") -> X | O3: =COUNTIF(C3:N3,"X") -> 4 | P3: =IF(O3>0,"Covered","Not covered") -> Covered
A4: =Requirements!A3 -> AC2 | B4: =Requirements!C3 -> Transfer is confirmed with a One-Time Password before execution. | C4: =IF(ISNUMBER(SEARCH($A4,'1.3 Test Cases'!$C$2)),"X","") -> X | D4: =IF(ISNUMBER(SEARCH($A4,'1.3 Test Cases'!$C$3)),"X","") | E4: =IF(ISNUMBER(SEARCH($A4,'1.3 Test Cases'!$C$4)),"X","") | F4: =IF(ISNUMBER(SEARCH($A4,'1.3 Test Cases'!$C$5)),"X","") | G4: =IF(ISNUMBER(SEARCH($A4,'1.3 Test Cases'!$C$6)),"X","") -> X | H4: =IF(ISNUMBER(SEARCH($A4,'1.3 Test Cases'!$C$7)),"X","") -> X | I4: =IF(ISNUMBER(SEARCH($A4,'1.3 Test Cases'!$C$8)),"X","") | J4: =IF(ISNUMBER(SEARCH($A4,'1.3 Test Cases'!$C$9)),"X","") | K4: =IF(ISNUMBER(SEARCH($A4,'1.3 Test Cases'!$C$10)),"X","") | L4: =IF(ISNUMBER(SEARCH($A4,'1.3 Test Cases'!$C$11)),"X","") | M4: =IF(ISNUMBER(SEARCH($A4,'1.3 Test Cases'!$C$12)),"X","") | N4: =IF(ISNUMBER(SEARCH($A4,'1.3 Test Cases'!$C$13)),"X","") | O4: =COUNTIF(C4:N4,"X") -> 3 | P4: =IF(O4>0,"Covered","Not covered") -> Covered
A5: =Requirements!A4 -> AC3 | B5: =Requirements!C4 -> A transfer fee is applied according to the bank's fee configuration. | C5: =IF(ISNUMBER(SEARCH($A5,'1.3 Test Cases'!$C$2)),"X","") -> X | D5: =IF(ISNUMBER(SEARCH($A5,'1.3 Test Cases'!$C$3)),"X","") | E5: =IF(ISNUMBER(SEARCH($A5,'1.3 Test Cases'!$C$4)),"X","") | F5: =IF(ISNUMBER(SEARCH($A5,'1.3 Test Cases'!$C$5)),"X","") -> X | G5: =IF(ISNUMBER(SEARCH($A5,'1.3 Test Cases'!$C$6)),"X","") | H5: =IF(ISNUMBER(SEARCH($A5,'1.3 Test Cases'!$C$7)),"X","") | I5: =IF(ISNUMBER(SEARCH($A5,'1.3 Test Cases'!$C$8)),"X","") | J5: =IF(ISNUMBER(SEARCH($A5,'1.3 Test Cases'!$C$9)),"X","") | K5: =IF(ISNUMBER(SEARCH($A5,'1.3 Test Cases'!$C$10)),"X","") | L5: =IF(ISNUMBER(SEARCH($A5,'1.3 Test Cases'!$C$11)),"X","") | M5: =IF(ISNUMBER(SEARCH($A5,'1.3 Test Cases'!$C$12)),"X","") | N5: =IF(ISNUMBER(SEARCH($A5,'1.3 Test Cases'!$C$13)),"X","") | O5: =COUNTIF(C5:N5,"X") -> 2 | P5: =IF(O5>0,"Covered","Not covered") -> Covered
A6: =Requirements!A5 -> AC4 | B6: =Requirements!C5 -> Daily transfer limit 20,000; per-transaction limit 10,000. | C6: =IF(ISNUMBER(SEARCH($A6,'1.3 Test Cases'!$C$2)),"X","") | D6: =IF(ISNUMBER(SEARCH($A6,'1.3 Test Cases'!$C$3)),"X","") -> X | E6: =IF(ISNUMBER(SEARCH($A6,'1.3 Test Cases'!$C$4)),"X","") -> X | F6: =IF(ISNUMBER(SEARCH($A6,'1.3 Test Cases'!$C$5)),"X","") | G6: =IF(ISNUMBER(SEARCH($A6,'1.3 Test Cases'!$C$6)),"X","") | H6: =IF(ISNUMBER(SEARCH($A6,'1.3 Test Cases'!$C$7)),"X","") | I6: =IF(ISNUMBER(SEARCH($A6,'1.3 Test Cases'!$C$8)),"X","") | J6: =IF(ISNUMBER(SEARCH($A6,'1.3 Test Cases'!$C$9)),"X","") | K6: =IF(ISNUMBER(SEARCH($A6,'1.3 Test Cases'!$C$10)),"X","") -> X | L6: =IF(ISNUMBER(SEARCH($A6,'1.3 Test Cases'!$C$11)),"X","") | M6: =IF(ISNUMBER(SEARCH($A6,'1.3 Test Cases'!$C$12)),"X","") | N6: =IF(ISNUMBER(SEARCH($A6,'1.3 Test Cases'!$C$13)),"X","") | O6: =COUNTIF(C6:N6,"X") -> 3 | P6: =IF(O6>0,"Covered","Not covered") -> Covered
A7: =Requirements!A6 -> AC5 | B7: =Requirements!C6 -> On success: source debited, reference generated, confirmation screen shown, confirmation SMS sent. | C7: =IF(ISNUMBER(SEARCH($A7,'1.3 Test Cases'!$C$2)),"X","") -> X | D7: =IF(ISNUMBER(SEARCH($A7,'1.3 Test Cases'!$C$3)),"X","") | E7: =IF(ISNUMBER(SEARCH($A7,'1.3 Test Cases'!$C$4)),"X","") | F7: =IF(ISNUMBER(SEARCH($A7,'1.3 Test Cases'!$C$5)),"X","") | G7: =IF(ISNUMBER(SEARCH($A7,'1.3 Test Cases'!$C$6)),"X","") | H7: =IF(ISNUMBER(SEARCH($A7,'1.3 Test Cases'!$C$7)),"X","") | I7: =IF(ISNUMBER(SEARCH($A7,'1.3 Test Cases'!$C$8)),"X","") -> X | J7: =IF(ISNUMBER(SEARCH($A7,'1.3 Test Cases'!$C$9)),"X","") | K7: =IF(ISNUMBER(SEARCH($A7,'1.3 Test Cases'!$C$10)),"X","") | L7: =IF(ISNUMBER(SEARCH($A7,'1.3 Test Cases'!$C$11)),"X","") | M7: =IF(ISNUMBER(SEARCH($A7,'1.3 Test Cases'!$C$12)),"X","") | N7: =IF(ISNUMBER(SEARCH($A7,'1.3 Test Cases'!$C$13)),"X","") | O7: =COUNTIF(C7:N7,"X") -> 2 | P7: =IF(O7>0,"Covered","Not covered") -> Covered
A8: =Requirements!A7 -> AC6 | B8: =Requirements!C7 -> If the transfer cannot be completed, the customer is shown an error message. | C8: =IF(ISNUMBER(SEARCH($A8,'1.3 Test Cases'!$C$2)),"X","") | D8: =IF(ISNUMBER(SEARCH($A8,'1.3 Test Cases'!$C$3)),"X","") -> X | E8: =IF(ISNUMBER(SEARCH($A8,'1.3 Test Cases'!$C$4)),"X","") -> X | F8: =IF(ISNUMBER(SEARCH($A8,'1.3 Test Cases'!$C$5)),"X","") -> X | G8: =IF(ISNUMBER(SEARCH($A8,'1.3 Test Cases'!$C$6)),"X","") -> X | H8: =IF(ISNUMBER(SEARCH($A8,'1.3 Test Cases'!$C$7)),"X","") | I8: =IF(ISNUMBER(SEARCH($A8,'1.3 Test Cases'!$C$8)),"X","") | J8: =IF(ISNUMBER(SEARCH($A8,'1.3 Test Cases'!$C$9)),"X","") -> X | K8: =IF(ISNUMBER(SEARCH($A8,'1.3 Test Cases'!$C$10)),"X","") | L8: =IF(ISNUMBER(SEARCH($A8,'1.3 Test Cases'!$C$11)),"X","") -> X | M8: =IF(ISNUMBER(SEARCH($A8,'1.3 Test Cases'!$C$12)),"X","") -> X | N8: =IF(ISNUMBER(SEARCH($A8,'1.3 Test Cases'!$C$13)),"X","") | O8: =COUNTIF(C8:N8,"X") -> 7 | P8: =IF(O8>0,"Covered","Not covered") -> Covered
A9: =Requirements!A8 -> IR1 | B9: =Requirements!C8 -> Insufficient funds are rejected before OTP, with the fee included in the balance check. | C9: =IF(ISNUMBER(SEARCH($A9,'1.3 Test Cases'!$C$2)),"X","") | D9: =IF(ISNUMBER(SEARCH($A9,'1.3 Test Cases'!$C$3)),"X","") | E9: =IF(ISNUMBER(SEARCH($A9,'1.3 Test Cases'!$C$4)),"X","") | F9: =IF(ISNUMBER(SEARCH($A9,'1.3 Test Cases'!$C$5)),"X","") -> X | G9: =IF(ISNUMBER(SEARCH($A9,'1.3 Test Cases'!$C$6)),"X","") | H9: =IF(ISNUMBER(SEARCH($A9,'1.3 Test Cases'!$C$7)),"X","") | I9: =IF(ISNUMBER(SEARCH($A9,'1.3 Test Cases'!$C$8)),"X","") | J9: =IF(ISNUMBER(SEARCH($A9,'1.3 Test Cases'!$C$9)),"X","") | K9: =IF(ISNUMBER(SEARCH($A9,'1.3 Test Cases'!$C$10)),"X","") | L9: =IF(ISNUMBER(SEARCH($A9,'1.3 Test Cases'!$C$11)),"X","") | M9: =IF(ISNUMBER(SEARCH($A9,'1.3 Test Cases'!$C$12)),"X","") | N9: =IF(ISNUMBER(SEARCH($A9,'1.3 Test Cases'!$C$13)),"X","") | O9: =COUNTIF(C9:N9,"X") -> 1 | P9: =IF(O9>0,"Covered","Not covered") -> Covered
A10: =Requirements!A9 -> IR2 | B10: =Requirements!C9 -> A failure after the debit loses no money: either nothing is debited or the debit is reversed automatically. | C10: =IF(ISNUMBER(SEARCH($A10,'1.3 Test Cases'!$C$2)),"X","") | D10: =IF(ISNUMBER(SEARCH($A10,'1.3 Test Cases'!$C$3)),"X","") | E10: =IF(ISNUMBER(SEARCH($A10,'1.3 Test Cases'!$C$4)),"X","") | F10: =IF(ISNUMBER(SEARCH($A10,'1.3 Test Cases'!$C$5)),"X","") | G10: =IF(ISNUMBER(SEARCH($A10,'1.3 Test Cases'!$C$6)),"X","") | H10: =IF(ISNUMBER(SEARCH($A10,'1.3 Test Cases'!$C$7)),"X","") | I10: =IF(ISNUMBER(SEARCH($A10,'1.3 Test Cases'!$C$8)),"X","") | J10: =IF(ISNUMBER(SEARCH($A10,'1.3 Test Cases'!$C$9)),"X","") -> X | K10: =IF(ISNUMBER(SEARCH($A10,'1.3 Test Cases'!$C$10)),"X","") | L10: =IF(ISNUMBER(SEARCH($A10,'1.3 Test Cases'!$C$11)),"X","") | M10: =IF(ISNUMBER(SEARCH($A10,'1.3 Test Cases'!$C$12)),"X","") | N10: =IF(ISNUMBER(SEARCH($A10,'1.3 Test Cases'!$C$13)),"X","") | O10: =COUNTIF(C10:N10,"X") -> 1 | P10: =IF(O10>0,"Covered","Not covered") -> Covered
A11: =Requirements!A10 -> IR3 | B11: =Requirements!C10 -> An OTP is valid only for the transfer details it was issued for. | C11: =IF(ISNUMBER(SEARCH($A11,'1.3 Test Cases'!$C$2)),"X","") | D11: =IF(ISNUMBER(SEARCH($A11,'1.3 Test Cases'!$C$3)),"X","") | E11: =IF(ISNUMBER(SEARCH($A11,'1.3 Test Cases'!$C$4)),"X","") | F11: =IF(ISNUMBER(SEARCH($A11,'1.3 Test Cases'!$C$5)),"X","") | G11: =IF(ISNUMBER(SEARCH($A11,'1.3 Test Cases'!$C$6)),"X","") | H11: =IF(ISNUMBER(SEARCH($A11,'1.3 Test Cases'!$C$7)),"X","") -> X | I11: =IF(ISNUMBER(SEARCH($A11,'1.3 Test Cases'!$C$8)),"X","") | J11: =IF(ISNUMBER(SEARCH($A11,'1.3 Test Cases'!$C$9)),"X","") | K11: =IF(ISNUMBER(SEARCH($A11,'1.3 Test Cases'!$C$10)),"X","") | L11: =IF(ISNUMBER(SEARCH($A11,'1.3 Test Cases'!$C$11)),"X","") | M11: =IF(ISNUMBER(SEARCH($A11,'1.3 Test Cases'!$C$12)),"X","") | N11: =IF(ISNUMBER(SEARCH($A11,'1.3 Test Cases'!$C$13)),"X","") | O11: =COUNTIF(C11:N11,"X") -> 1 | P11: =IF(O11>0,"Covered","Not covered") -> Covered
A12: =Requirements!A11 -> IR4 | B12: =Requirements!C11 -> A duplicate submission or retry results in at most one debit. | C12: =IF(ISNUMBER(SEARCH($A12,'1.3 Test Cases'!$C$2)),"X","") | D12: =IF(ISNUMBER(SEARCH($A12,'1.3 Test Cases'!$C$3)),"X","") | E12: =IF(ISNUMBER(SEARCH($A12,'1.3 Test Cases'!$C$4)),"X","") | F12: =IF(ISNUMBER(SEARCH($A12,'1.3 Test Cases'!$C$5)),"X","") | G12: =IF(ISNUMBER(SEARCH($A12,'1.3 Test Cases'!$C$6)),"X","") | H12: =IF(ISNUMBER(SEARCH($A12,'1.3 Test Cases'!$C$7)),"X","") | I12: =IF(ISNUMBER(SEARCH($A12,'1.3 Test Cases'!$C$8)),"X","") -> X | J12: =IF(ISNUMBER(SEARCH($A12,'1.3 Test Cases'!$C$9)),"X","") | K12: =IF(ISNUMBER(SEARCH($A12,'1.3 Test Cases'!$C$10)),"X","") | L12: =IF(ISNUMBER(SEARCH($A12,'1.3 Test Cases'!$C$11)),"X","") | M12: =IF(ISNUMBER(SEARCH($A12,'1.3 Test Cases'!$C$12)),"X","") | N12: =IF(ISNUMBER(SEARCH($A12,'1.3 Test Cases'!$C$13)),"X","") | O12: =COUNTIF(C12:N12,"X") -> 1 | P12: =IF(O12>0,"Covered","Not covered") -> Covered
A13: =Requirements!A12 -> IR5 | B13: =Requirements!C12 -> Limits hold when transfers are submitted at the same time. | C13: =IF(ISNUMBER(SEARCH($A13,'1.3 Test Cases'!$C$2)),"X","") | D13: =IF(ISNUMBER(SEARCH($A13,'1.3 Test Cases'!$C$3)),"X","") | E13: =IF(ISNUMBER(SEARCH($A13,'1.3 Test Cases'!$C$4)),"X","") | F13: =IF(ISNUMBER(SEARCH($A13,'1.3 Test Cases'!$C$5)),"X","") | G13: =IF(ISNUMBER(SEARCH($A13,'1.3 Test Cases'!$C$6)),"X","") | H13: =IF(ISNUMBER(SEARCH($A13,'1.3 Test Cases'!$C$7)),"X","") | I13: =IF(ISNUMBER(SEARCH($A13,'1.3 Test Cases'!$C$8)),"X","") | J13: =IF(ISNUMBER(SEARCH($A13,'1.3 Test Cases'!$C$9)),"X","") | K13: =IF(ISNUMBER(SEARCH($A13,'1.3 Test Cases'!$C$10)),"X","") -> X | L13: =IF(ISNUMBER(SEARCH($A13,'1.3 Test Cases'!$C$11)),"X","") | M13: =IF(ISNUMBER(SEARCH($A13,'1.3 Test Cases'!$C$12)),"X","") | N13: =IF(ISNUMBER(SEARCH($A13,'1.3 Test Cases'!$C$13)),"X","") | O13: =COUNTIF(C13:N13,"X") -> 1 | P13: =IF(O13>0,"Covered","Not covered") -> Covered
A14: =Requirements!A13 -> IR6 | B14: =Requirements!C13 -> A customer can transfer only from their own accounts to their own registered beneficiaries (enforced by the service, not just the UI). | C14: =IF(ISNUMBER(SEARCH($A14,'1.3 Test Cases'!$C$2)),"X","") | D14: =IF(ISNUMBER(SEARCH($A14,'1.3 Test Cases'!$C$3)),"X","") | E14: =IF(ISNUMBER(SEARCH($A14,'1.3 Test Cases'!$C$4)),"X","") | F14: =IF(ISNUMBER(SEARCH($A14,'1.3 Test Cases'!$C$5)),"X","") | G14: =IF(ISNUMBER(SEARCH($A14,'1.3 Test Cases'!$C$6)),"X","") | H14: =IF(ISNUMBER(SEARCH($A14,'1.3 Test Cases'!$C$7)),"X","") | I14: =IF(ISNUMBER(SEARCH($A14,'1.3 Test Cases'!$C$8)),"X","") | J14: =IF(ISNUMBER(SEARCH($A14,'1.3 Test Cases'!$C$9)),"X","") | K14: =IF(ISNUMBER(SEARCH($A14,'1.3 Test Cases'!$C$10)),"X","") | L14: =IF(ISNUMBER(SEARCH($A14,'1.3 Test Cases'!$C$11)),"X","") | M14: =IF(ISNUMBER(SEARCH($A14,'1.3 Test Cases'!$C$12)),"X","") | N14: =IF(ISNUMBER(SEARCH($A14,'1.3 Test Cases'!$C$13)),"X","") -> X | O14: =COUNTIF(C14:N14,"X") -> 1 | P14: =IF(O14>0,"Covered","Not covered") -> Covered
B15: =COUNTIF(P3:P14,"Covered")&" of "&ROWS(P3:P14)&" covered" -> 12 of 12 covered
A17: Risk coverage: risks -> test cases
A18: ID | B18: Description | C18: TC01 | D18: TC02 | E18: TC03 | F18: TC04 | G18: TC05 | H18: TC06 | I18: TC07 | J18: TC08 | K18: TC09 | L18: TC10 | M18: TC11 | N18: TC12 | O18: Tests | P18: Coverage | Q18: Rating
A19: ='1.2 Risk Register'!A2 -> R1 | B19: ='1.2 Risk Register'!B2 -> Partial failure: account debited but transfer fails, no reversal, customer retries | C19: =IF(ISNUMBER(SEARCH($A19,'1.3 Test Cases'!$D$2)),"X","") -> X | D19: =IF(ISNUMBER(SEARCH($A19,'1.3 Test Cases'!$D$3)),"X","") | E19: =IF(ISNUMBER(SEARCH($A19,'1.3 Test Cases'!$D$4)),"X","") | F19: =IF(ISNUMBER(SEARCH($A19,'1.3 Test Cases'!$D$5)),"X","") | G19: =IF(ISNUMBER(SEARCH($A19,'1.3 Test Cases'!$D$6)),"X","") | H19: =IF(ISNUMBER(SEARCH($A19,'1.3 Test Cases'!$D$7)),"X","") | I19: =IF(ISNUMBER(SEARCH($A19,'1.3 Test Cases'!$D$8)),"X","") -> X | J19: =IF(ISNUMBER(SEARCH($A19,'1.3 Test Cases'!$D$9)),"X","") -> X | K19: =IF(ISNUMBER(SEARCH($A19,'1.3 Test Cases'!$D$10)),"X","") | L19: =IF(ISNUMBER(SEARCH($A19,'1.3 Test Cases'!$D$11)),"X","") | M19: =IF(ISNUMBER(SEARCH($A19,'1.3 Test Cases'!$D$12)),"X","") | N19: =IF(ISNUMBER(SEARCH($A19,'1.3 Test Cases'!$D$13)),"X","") | O19: =COUNTIF(C19:N19,"X") -> 3 | P19: =IF(O19>0,"Covered","Not covered") -> Covered | Q19: ='1.2 Risk Register'!G2 -> High
A20: ='1.2 Risk Register'!A3 -> R2 | B20: ='1.2 Risk Register'!B3 -> Limits not enforced correctly (boundary, daily window, pending transfers, simultaneous requests) | C20: =IF(ISNUMBER(SEARCH($A20,'1.3 Test Cases'!$D$2)),"X","") | D20: =IF(ISNUMBER(SEARCH($A20,'1.3 Test Cases'!$D$3)),"X","") -> X | E20: =IF(ISNUMBER(SEARCH($A20,'1.3 Test Cases'!$D$4)),"X","") -> X | F20: =IF(ISNUMBER(SEARCH($A20,'1.3 Test Cases'!$D$5)),"X","") | G20: =IF(ISNUMBER(SEARCH($A20,'1.3 Test Cases'!$D$6)),"X","") | H20: =IF(ISNUMBER(SEARCH($A20,'1.3 Test Cases'!$D$7)),"X","") | I20: =IF(ISNUMBER(SEARCH($A20,'1.3 Test Cases'!$D$8)),"X","") | J20: =IF(ISNUMBER(SEARCH($A20,'1.3 Test Cases'!$D$9)),"X","") | K20: =IF(ISNUMBER(SEARCH($A20,'1.3 Test Cases'!$D$10)),"X","") -> X | L20: =IF(ISNUMBER(SEARCH($A20,'1.3 Test Cases'!$D$11)),"X","") | M20: =IF(ISNUMBER(SEARCH($A20,'1.3 Test Cases'!$D$12)),"X","") -> X | N20: =IF(ISNUMBER(SEARCH($A20,'1.3 Test Cases'!$D$13)),"X","") | O20: =COUNTIF(C20:N20,"X") -> 4 | P20: =IF(O20>0,"Covered","Not covered") -> Covered | Q20: ='1.2 Risk Register'!G3 -> High
A21: ='1.2 Risk Register'!A4 -> R3 | B21: ='1.2 Risk Register'!B4 -> OTP does not protect the transfer the customer actually approved | C21: =IF(ISNUMBER(SEARCH($A21,'1.3 Test Cases'!$D$2)),"X","") | D21: =IF(ISNUMBER(SEARCH($A21,'1.3 Test Cases'!$D$3)),"X","") | E21: =IF(ISNUMBER(SEARCH($A21,'1.3 Test Cases'!$D$4)),"X","") | F21: =IF(ISNUMBER(SEARCH($A21,'1.3 Test Cases'!$D$5)),"X","") | G21: =IF(ISNUMBER(SEARCH($A21,'1.3 Test Cases'!$D$6)),"X","") -> X | H21: =IF(ISNUMBER(SEARCH($A21,'1.3 Test Cases'!$D$7)),"X","") -> X | I21: =IF(ISNUMBER(SEARCH($A21,'1.3 Test Cases'!$D$8)),"X","") | J21: =IF(ISNUMBER(SEARCH($A21,'1.3 Test Cases'!$D$9)),"X","") | K21: =IF(ISNUMBER(SEARCH($A21,'1.3 Test Cases'!$D$10)),"X","") | L21: =IF(ISNUMBER(SEARCH($A21,'1.3 Test Cases'!$D$11)),"X","") | M21: =IF(ISNUMBER(SEARCH($A21,'1.3 Test Cases'!$D$12)),"X","") | N21: =IF(ISNUMBER(SEARCH($A21,'1.3 Test Cases'!$D$13)),"X","") | O21: =COUNTIF(C21:N21,"X") -> 2 | P21: =IF(O21>0,"Covered","Not covered") -> Covered | Q21: ='1.2 Risk Register'!G4 -> High
A22: ='1.2 Risk Register'!A5 -> R4 | B22: ='1.2 Risk Register'!B5 -> Account-ownership checks: customer can only use their own accounts and beneficiaries | C22: =IF(ISNUMBER(SEARCH($A22,'1.3 Test Cases'!$D$2)),"X","") | D22: =IF(ISNUMBER(SEARCH($A22,'1.3 Test Cases'!$D$3)),"X","") | E22: =IF(ISNUMBER(SEARCH($A22,'1.3 Test Cases'!$D$4)),"X","") | F22: =IF(ISNUMBER(SEARCH($A22,'1.3 Test Cases'!$D$5)),"X","") | G22: =IF(ISNUMBER(SEARCH($A22,'1.3 Test Cases'!$D$6)),"X","") | H22: =IF(ISNUMBER(SEARCH($A22,'1.3 Test Cases'!$D$7)),"X","") | I22: =IF(ISNUMBER(SEARCH($A22,'1.3 Test Cases'!$D$8)),"X","") | J22: =IF(ISNUMBER(SEARCH($A22,'1.3 Test Cases'!$D$9)),"X","") | K22: =IF(ISNUMBER(SEARCH($A22,'1.3 Test Cases'!$D$10)),"X","") | L22: =IF(ISNUMBER(SEARCH($A22,'1.3 Test Cases'!$D$11)),"X","") | M22: =IF(ISNUMBER(SEARCH($A22,'1.3 Test Cases'!$D$12)),"X","") -> X | N22: =IF(ISNUMBER(SEARCH($A22,'1.3 Test Cases'!$D$13)),"X","") -> X | O22: =COUNTIF(C22:N22,"X") -> 2 | P22: =IF(O22>0,"Covered","Not covered") -> Covered | Q22: ='1.2 Risk Register'!G5 -> High
A23: ='1.2 Risk Register'!A6 -> R5 | B23: ='1.2 Risk Register'!B6 -> Misleading result: generic error when money moved, or success SMS for a failed transfer | C23: =IF(ISNUMBER(SEARCH($A23,'1.3 Test Cases'!$D$2)),"X","") -> X | D23: =IF(ISNUMBER(SEARCH($A23,'1.3 Test Cases'!$D$3)),"X","") | E23: =IF(ISNUMBER(SEARCH($A23,'1.3 Test Cases'!$D$4)),"X","") | F23: =IF(ISNUMBER(SEARCH($A23,'1.3 Test Cases'!$D$5)),"X","") | G23: =IF(ISNUMBER(SEARCH($A23,'1.3 Test Cases'!$D$6)),"X","") | H23: =IF(ISNUMBER(SEARCH($A23,'1.3 Test Cases'!$D$7)),"X","") | I23: =IF(ISNUMBER(SEARCH($A23,'1.3 Test Cases'!$D$8)),"X","") | J23: =IF(ISNUMBER(SEARCH($A23,'1.3 Test Cases'!$D$9)),"X","") -> X | K23: =IF(ISNUMBER(SEARCH($A23,'1.3 Test Cases'!$D$10)),"X","") | L23: =IF(ISNUMBER(SEARCH($A23,'1.3 Test Cases'!$D$11)),"X","") | M23: =IF(ISNUMBER(SEARCH($A23,'1.3 Test Cases'!$D$12)),"X","") | N23: =IF(ISNUMBER(SEARCH($A23,'1.3 Test Cases'!$D$13)),"X","") | O23: =COUNTIF(C23:N23,"X") -> 2 | P23: =IF(O23>0,"Covered","Not covered") -> Covered | Q23: ='1.2 Risk Register'!G6 -> High
A24: ='1.2 Risk Register'!A7 -> R6 | B24: ='1.2 Risk Register'!B7 -> Fee or amount mismatch, or rounding | C24: =IF(ISNUMBER(SEARCH($A24,'1.3 Test Cases'!$D$2)),"X","") -> X | D24: =IF(ISNUMBER(SEARCH($A24,'1.3 Test Cases'!$D$3)),"X","") | E24: =IF(ISNUMBER(SEARCH($A24,'1.3 Test Cases'!$D$4)),"X","") | F24: =IF(ISNUMBER(SEARCH($A24,'1.3 Test Cases'!$D$5)),"X","") -> X | G24: =IF(ISNUMBER(SEARCH($A24,'1.3 Test Cases'!$D$6)),"X","") | H24: =IF(ISNUMBER(SEARCH($A24,'1.3 Test Cases'!$D$7)),"X","") | I24: =IF(ISNUMBER(SEARCH($A24,'1.3 Test Cases'!$D$8)),"X","") | J24: =IF(ISNUMBER(SEARCH($A24,'1.3 Test Cases'!$D$9)),"X","") | K24: =IF(ISNUMBER(SEARCH($A24,'1.3 Test Cases'!$D$10)),"X","") | L24: =IF(ISNUMBER(SEARCH($A24,'1.3 Test Cases'!$D$11)),"X","") -> X | M24: =IF(ISNUMBER(SEARCH($A24,'1.3 Test Cases'!$D$12)),"X","") | N24: =IF(ISNUMBER(SEARCH($A24,'1.3 Test Cases'!$D$13)),"X","") | O24: =COUNTIF(C24:N24,"X") -> 3 | P24: =IF(O24>0,"Covered","Not covered") -> Covered | Q24: ='1.2 Risk Register'!G7 -> Medium
B25: =COUNTIF(P19:P24,"Covered")&" of "&ROWS(P19:P24)&" covered" -> 6 of 6 covered
B27: Green cells are linked from other sheets. Both matrices update automatically from the Requirement and Risk columns of 1.3 Test Cases.

Sheet 1.4 Coverage
A1: Deliberately not covered
A2: Area | B2: Reason
A3: Beneficiary registration | B3: Separate feature; this story starts from an already registered beneficiary.
A4: Performance and load | B4: Needs its own plan with agreed volumes; raised separately rather than squeezed into 12 cases.
A5: Look and feel, accessibility, devices, localisation | B5: Important, but they do not decide whether money moves correctly. Covered by general regression and a device matrix.
A6: SMS gateway failure, cut-off times, holidays | B6: Waiting on answers to the questions in 1.1.
A7: Purpose-code rules | B7: Blocked by the contradiction raised in Q12.
A9: Automated vs manual
A10: Test cases | B10: Decision and reason
A11: TC02, TC03, TC04, TC07, TC09, TC10, TC11, TC12 | B11: Automate at API level in the regression suite: deterministic rules, many data combinations, high cost if they regress. TC09 cannot be done reliably by hand.
A12: TC05, TC06 | B12: Automate once an OTP test hook exists in the test environment (question raised).
A13: TC01 | B13: Thin automated UI smoke on every build; SMS content and on-screen wording checked manually (needs a real device and judgement).
A14: TC08 | B14: Manual with developer support for failure injection; automate once a stub is available.
A16: Release criteria: how I would know it is safe
A17: Criterion | B17: Measure
A18: Test results | B18: All 12 cases pass on the release build in an environment connected to core banking (not only mocks).
A19: Open defects | B19: Zero open severity 1-2 defects in money movement, limits, OTP or authorisation.
A20: Reconciliation | B20: Across the full test run, debits = credits + fees, with nothing left in suspense.
A21: Open questions | B21: Q1-Q12 answered, or the assumptions formally accepted by the Product Owner.
A22: Sign-offs | B22: Bank UAT signed off; security and performance owners have signed off their areas.
A23: Operational readiness | B23: Monitoring for failed or stuck transfers live; feature can be switched off.
